rnd/__init__.py
rnd/__main__.py
rnd/cli.py
rnd/core.py
rnd/presets.py
rnd/test.py
rnd-1.0.1.dist-info/METADATA
rnd-1.0.1.dist-info/WHEEL
rnd-1.0.1.dist-info/entry_points.txt
rnd-1.0.1.dist-info/top_level.txt
rnd-1.0.1.dist-info/RECORD
