Metadata-Version: 2.4
Name: rnd
Version: 1.0.1
Summary: An advanced, customizable random string generator without using random or string.
Author-email: Crazy <demonking0688@gmail.com>
License: MIT
Project-URL: Homepage, https://pypi.org/project/rnd/
Keywords: random,string,generator,emojis,secure,password,rnd
Classifier: Programming Language :: Python :: 3
Classifier: License :: OSI Approved :: MIT License
Classifier: Operating System :: OS Independent
Requires-Python: >=3.7
